{
 "actions": [],
 "allow_rename": 1,
 "creation": "2026-06-12 09:17:14.000000",
 "doctype": "DocType",
 "editable_grid": 1,
 "engine": "InnoDB",
 "field_order": [
  "tool",
  "required",
  "description"
 ],
 "fields": [
  {
   "fieldname": "tool",
   "fieldtype": "Link",
   "in_list_view": 1,
   "label": "Tool",
   "options": "Agent Tool Function",
   "reqd": 1
  },
  {
   "default": "0",
   "fieldname": "required",
   "fieldtype": "Check",
   "in_list_view": 1,
   "label": "Required"
  },
  {
   "description": "Override the tool description for this skill.",
   "fieldname": "description",
   "fieldtype": "Small Text",
   "label": "Description"
  }
 ],
 "grid_page_length": 50,
 "index_web_pages_for_search": 1,
 "istable": 1,
 "links": [],
 "modified": "2026-06-12 09:17:14.000000",
 "modified_by": "Administrator",
 "module": "Huf",
 "name": "Skill Tool",
 "owner": "Administrator",
 "permissions": [],
 "row_format": "Dynamic",
 "sort_field": "modified",
 "sort_order": "DESC",
 "states": []
}
